cgr/__init__.py
cgr_view-0.0.1.dev2.dist-info/LICENSE.txt
cgr_view-0.0.1.dev2.dist-info/METADATA
cgr_view-0.0.1.dev2.dist-info/WHEEL
cgr_view-0.0.1.dev2.dist-info/top_level.txt
cgr_view-0.0.1.dev2.dist-info/RECORD
